rename_github_default_branch.py
rename_github_default_branch-0.0.3.dist-info/LICENSE
rename_github_default_branch-0.0.3.dist-info/METADATA
rename_github_default_branch-0.0.3.dist-info/WHEEL
rename_github_default_branch-0.0.3.dist-info/entry_points.txt
rename_github_default_branch-0.0.3.dist-info/top_level.txt
rename_github_default_branch-0.0.3.dist-info/RECORD
