Metadata-Version: 2.1
Name: rename-github-default-branch
Version: 0.0.3
Summary: A Python script for bulk renaming the default branch of your GitHub repositories using the API
Home-page: https://github.com/dfm/rename_github_default_branch
Author: Dan Foreman-Mackey
Author-email: foreman.mackey@gmail.com
License: MIT
Platform: UNKNOWN
Classifier: Development Status :: 4 - Beta
Classifier: Environment :: Console
Classifier: Intended Audience :: Developers
Classifier: License :: OSI Approved :: MIT License
Classifier: Operating System :: OS Independent
Classifier: Programming Language :: Python
Classifier: Programming Language :: Python :: 3.6
Classifier: Programming Language :: Python :: 3.7
Classifier: Programming Language :: Python :: 3 :: Only
Classifier: Topic :: Software Development :: Libraries :: Python Modules
Classifier: Topic :: Software Development :: Quality Assurance
Requires-Python: >=3.6
Requires-Dist: requests
Requires-Dist: click
Requires-Dist: tqdm
